mongomasker_cli/main.py
mongomasker_cli-0.5.4.dist-info/LICENSE
mongomasker_cli-0.5.4.dist-info/METADATA
mongomasker_cli-0.5.4.dist-info/WHEEL
mongomasker_cli-0.5.4.dist-info/entry_points.txt
mongomasker_cli-0.5.4.dist-info/RECORD
