Metadata-Version: 2.3
Name: mongomasker_cli
Version: 0.5.4
Summary: MongoMasker is a tool designed to anonymize specified fields in a MongoDB collection. It uses the `faker` library to generate realistic fake data, processes documents in batches for improved performance, and leverages asynchronous processing with `motor` for efficiency.
License: MIT
Author: Zeeshan Khan
Author-email: zkhan1093@gmail.com
Requires-Python: >=3.10,<4.0
Classifier: License :: OSI Approved :: MIT License
Classifier: Programming Language :: Python :: 3
Classifier: Programming Language :: Python :: 3.10
Classifier: Programming Language :: Python :: 3.11
Classifier: Programming Language :: Python :: 3.12
Classifier: Programming Language :: Python :: 3.13
Requires-Dist: click (<8.2)
Requires-Dist: faker (>=26.0.0,<27.0.0)
Requires-Dist: motor (>=3.5.0,<4.0.0)
Requires-Dist: pymongo (==4.8.0)
Requires-Dist: typer (>=0.12.3,<0.13.0)
Project-URL: Repository, https://github.com/zkhan93/mongomasker-cli
